{
  "recipe": {
    "@context": "http://schema.org/",
    "@type": "Recipe",
    "name": "Супа от телешка глава",
    "image": [],
    "datePublished": "",
    "cookTime": "PT1H30M",
    "recipeYield": "4 servings",
    "recipeCategory": "Супи - други",
    "nutrition": {},
    "recipeIngredient": [
      "1 телешка глава",
      "1 глава лук",
      "2 моркова",
      "1 глава целина",
      "6 домата",
      "1 яйце",
      "1 ч.ч. кисело мляко",
      "1 дафинов лист",
      " черен пипер",
      " сол"
    ],
    "recipeInstructions": [
      {
        "@type": "HowToStep",
        "text": "Телешката глава се разсича на няколко парчета, които се заливат в вода в дълбока тенджера и се слагат да се варят. Щом водата заври, супата се посолява."
      },
      {
        "@type": "HowToStep",
        "text": "След един час се прибавят ситно нарязаните лук, моркови, целина, а също и дафиновият лист."
      },
      {
        "@type": "HowToStep",
        "text": "Когато месото започне да се отделя от костите, то се обира и нарязва. Бульонът се прецежда и се отново се слага на огъня със зеленчуците и нарязаното месо."
      },
      {
        "@type": "HowToStep",
        "text": "Щом бульонът заври, се прибавят настърганите домати."
      },
      {
        "@type": "HowToStep",
        "text": "След 10 минути супата се застройва с разбитите кисело мляко и яйце и се поръсва с черен пипер. Сервира се гореща."
      }
    ]
  },
  "ingredients": [
    {
      "name": "телешка глава",
      "qty": "1",
      "id": 27
    },
    {
      "name": "глава лук",
      "qty": "1",
      "id": 3
    },
    {
      "name": "моркова",
      "qty": "2",
      "id": 13
    },
    {
      "name": "глава целина",
      "qty": "1",
      "id": 30
    },
    {
      "name": "домата",
      "qty": "6",
      "id": 15
    },
    {
      "name": "яйце",
      "qty": "1",
      "id": 5
    },
    {
      "name": "кисело мляко",
      "qty": "1 ч.ч.",
      "id": 21
    },
    {
      "name": "дафинов лист",
      "qty": "1",
      "id": 70
    },
    {
      "name": "черен пипер",
      "qty": "",
      "id": 2
    },
    {
      "name": "сол",
      "qty": "",
      "id": 1
    }
  ]
}