{
  "recipe": {
    "@context": "http://schema.org/",
    "@type": "Recipe",
    "name": "Салата от китайско зеле, грейпфрут, зелен боб и скариди",
    "image": [
      "http://www.1001recepti.com/images/photos/recipes/size_4/salata-snejen-vruh-1-[11].jpg",
      "http://www.1001recepti.com/images/photos/recipes/size_2/salata-snejen-vruh-1-[11].jpg",
      "http://www.1001recepti.com/images/photos/recipes/size_3/salata-snejen-vruh-1-[11].jpg"
    ],
    "datePublished": "2011-04-04",
    "cookTime": "PT0H5M",
    "recipeYield": "4 servings",
    "recipeCategory": "Салати",
    "nutrition": {
      "@type": "NutritionInformation",
      "calories": "179 calories",
      "carbohydrateContent": "11 g",
      "fatContent": "9 g",
      "proteinContent": "13 g",
      "saturatedFatContent": "4 g",
      "unsaturatedFatContent": "3.821375 g",
      "cholesterolContent": "79 mg"
    },
    "recipeIngredient": [
      "1/2 кг китайско зеле",
      "1  грейпфрут",
      "100 г зелен боб",
      "150 броя скариди",
      "100 г сирене",
      "2 с.л. зехтин",
      "2 с.л. лимонов сок",
      "сол"
    ],
    "recipeInstructions": [
      {
        "@type": "HowToStep",
        "text": "Скаридите (150 броя) и зеленият боб (100 г) се сваряват.Шайбите от грейпфрута (1 бр) се режат на половинки и нареждат в кръг в края на чинията."
      },
      {
        "@type": "HowToStep",
        "text": "Зелето (1/2 кг) се накъсва и оформя като планински връх. От него се „спускат” 6-те бобени шушулки, между които се поставят скаридите (150 броя). Сиренето (100 г) се настъргва така, че да „заснежи” върха."
      },
      {
        "@type": "HowToStep",
        "text": "Салатата се овкусява със сол, зехтин и лимонов сок."
      }
    ]
  },
  "ingredients": [
    {
      "name": "китайско зеле",
      "qty": "1/2 кг",
      "id": 233
    },
    {
      "name": "грейпфрут",
      "qty": "1",
      "id": 286
    },
    {
      "name": "зелен боб",
      "qty": "100 г",
      "id": 99
    },
    {
      "name": "скариди",
      "qty": "150 броя",
      "id": 104
    },
    {
      "name": "сирене",
      "qty": "100 г",
      "id": 32
    },
    {
      "name": "зехтин",
      "qty": "2 с.л.",
      "id": 10
    },
    {
      "name": "лимонов сок",
      "qty": "2 с.л.",
      "id": 17
    },
    {
      "name": "сол",
      "qty": "Parsing error",
      "id": 1
    }
  ]
}