{
  "recipe": {
    "@context": "http://schema.org/",
    "@type": "Recipe",
    "name": "Коктейл Джин Рики (Gin Rickey)",
    "image": [
      "http://www.1001recepti.com/images/photos/recipes/size_4/kokteil-djin-riki--1-[1607].jpg",
      "http://www.1001recepti.com/images/photos/recipes/size_2/kokteil-djin-riki--1-[1607].jpg",
      "http://www.1001recepti.com/images/photos/recipes/size_3/kokteil-djin-riki--1-[1607].jpg"
    ],
    "datePublished": "2013-02-17",
    "cookTime": "PT0H5M",
    "recipeYield": "1 servings",
    "recipeCategory": "Коктейли",
    "nutrition": {
      "@type": "NutritionInformation",
      "calories": "115 calories",
      "carbohydrateContent": "3 g",
      "fatContent": "0 g",
      "proteinContent": "0 g",
      "saturatedFatContent": "0 g",
      "unsaturatedFatContent": "0.01595 g",
      "cholesterolContent": "0 mg"
    },
    "recipeIngredient": [
      "50 мл. джин",
      "1/2  лайм",
      "150 мл. газирана вода"
    ],
    "recipeInstructions": [
      {
        "@type": "HowToStep",
        "text": "Лаймът (1/2 бр) се изстисква и сокът му заедно с джина (50 мл.) се сипват във висока чаша с лед. Чашата се допълва догоре с газирана вода (150 мл.) и се украсява с резен лайм."
      }
    ]
  },
  "ingredients": [
    {
      "name": "джин",
      "qty": "50 мл.",
      "id": 192
    },
    {
      "name": "лайм",
      "qty": "1/2",
      "id": 204
    },
    {
      "name": "газирана вода",
      "qty": "150 мл.",
      "id": 199
    }
  ]
}