{
  "recipe": {
    "@context": "http://schema.org/",
    "@type": "Recipe",
    "name": "Индийско къри с пиле и гарам масала",
    "image": [
      "http://www.1001recepti.com/images/photos/recipes/size_4/indiisko-kuri-s-pile-i-garam-masala-3-[2319].jpg",
      "http://www.1001recepti.com/images/photos/recipes/size_2/indiisko-kuri-s-pile-i-garam-masala-3-[2319].jpg",
      "http://www.1001recepti.com/images/photos/recipes/size_3/indiisko-kuri-s-pile-i-garam-masala-3-[2319].jpg"
    ],
    "datePublished": "2013-02-17",
    "cookTime": "PT1H0M",
    "recipeYield": "4 servings",
    "recipeCategory": "Основни",
    "nutrition": {
      "@type": "NutritionInformation",
      "calories": "579 calories",
      "carbohydrateContent": "13 g",
      "fatContent": "43 g",
      "proteinContent": "33 g",
      "saturatedFatContent": "14 g",
      "unsaturatedFatContent": "25.129745 g",
      "cholesterolContent": "152 mg"
    },
    "recipeIngredient": [
      "600 г пиле",
      "3 ч.л. гарам масала",
      "400 мл. кисело мляко",
      "1 глава лук",
      "2 скилидки чесън",
      "1 с.л. джинджифил",
      "6 с.л. зехтин",
      "300 г домати от консерва",
      "100 мл. сметана",
      "1 ч.л. лют пипер"
    ],
    "recipeInstructions": [
      {
        "@type": "HowToStep",
        "text": "В дълбок съд се изсипва киселото мляко (400 мл.) и масалата (3 ч.л.) и се разбърква до получаване на еднородна смес. Слага се нарязано на едри парчета пилешко месо (600 г) и се маринова в хладилник между 30 и 60 минути. Междувременно в пасатор се смилат лукът (1 глава), чесънът (2 скилидки), джинджифилът (1 с.л.) и малко зехтин до получаване на еднородна смес."
      },
      {
        "@type": "HowToStep",
        "text": "В сгорещен тиган се изсипва пилето, заедно с маринатата и малко зехтин. Задушава се за 4-5 минути до полуготовност. След това сместа се отстранява и в тигана се изсипва пасираният сос. Задушава се за 3-4 минути, докато течността се изпари и лукът промени цвета си. Трябва да се внимава да не загори, като при необходимост се добавя още малко зехтин. Поръсва се с лют пипер (1 ч.л.) и се добавят доматите и сметаната. Разбърква се и щом заври се добавя полуготовото пиле. Овкусява се със сол и се готви още 4-5 минути. Ако предпочитате ястие с повече сос, се добавя малко вода."
      },
      {
        "@type": "HowToStep",
        "text": "Кърито се сервира върху сварен или приготвен на пара ориз."
      },
      {
        "@type": "HowToStep",
        "text": "Забележка: Ако не разполагате с гарам масала, можете да си направите по тази <a href=http://www.1001recepti.com/recipe/?recipe_id=2320-garam-masala>рецепта за гарам масала</a>."
      }
    ]
  },
  "ingredients": [
    {
      "name": "пиле",
      "qty": "600 г",
      "id": 111
    },
    {
      "name": "гарам масала",
      "qty": "3 ч.л.",
      "id": 27
    },
    {
      "name": "кисело мляко",
      "qty": "400 мл.",
      "id": 21
    },
    {
      "name": "лук",
      "qty": "1 глава",
      "id": 3
    },
    {
      "name": "чесън",
      "qty": "2 скилидки",
      "id": 6
    },
    {
      "name": "джинджифил",
      "qty": "1 с.л.",
      "id": 84
    },
    {
      "name": "зехтин",
      "qty": "6 с.л.",
      "id": 10
    },
    {
      "name": "домати от консерва",
      "qty": "300 г",
      "id": 86
    },
    {
      "name": "сметана",
      "qty": "100 мл.",
      "id": 19
    },
    {
      "name": "лют пипер",
      "qty": "1 ч.л.",
      "id": 132
    }
  ]
}