{
  "recipe": {
    "@context": "http://schema.org/",
    "@type": "Recipe",
    "name": "Лесна паста (макарони) с чери домати, чесън, зехтин и босилек",
    "image": [
      "http://www.1001recepti.com/images/photos/recipes/size_4/pasta-s-cheri-domati-2-[2514].jpg",
      "http://www.1001recepti.com/images/photos/recipes/size_2/pasta-s-cheri-domati-2-[2514].jpg",
      "http://www.1001recepti.com/images/photos/recipes/size_3/pasta-s-cheri-domati-2-[2514].jpg"
    ],
    "datePublished": "2013-05-31",
    "cookTime": "PT0H35M",
    "recipeYield": "4 servings",
    "recipeCategory": "Предястия",
    "nutrition": {
      "@type": "NutritionInformation",
      "calories": "390 calories",
      "carbohydrateContent": "61 g",
      "fatContent": "11 g",
      "proteinContent": "10 g",
      "saturatedFatContent": "1 g",
      "unsaturatedFatContent": "8.443355 g",
      "cholesterolContent": "0 mg"
    },
    "recipeIngredient": [
      "300 г паста",
      "300 г чери домати",
      "6 скилидки чесън",
      "6 с.л. зехтин",
      "1 щип. черен пипер",
      "босилек",
      "сол"
    ],
    "recipeInstructions": [
      {
        "@type": "HowToStep",
        "text": "Пастата (300 г) се сварява в подсолена вода според указанията на опаковката. След това се отцежда."
      },
      {
        "@type": "HowToStep",
        "text": "Чери доматите (300 г) се измиват старателно и се разполовяват. Поставят се в дълбок тиган със зехтин (6 с.л.) и се задушават, заедно с пресования чесън (6 скилидки)  на тих огън. Щом доматите омекнат, към тях се прибавя сварената и отцедена паста и се бърка, докато ароматите се смесят. Ястието се овкусява със сол и черен пипер (1 щип.) и се сервира горещо. По желание се декорира с пресен босилек. "
      }
    ]
  },
  "ingredients": [
    {
      "name": "паста",
      "qty": "300 г",
      "id": 55
    },
    {
      "name": "чери домати",
      "qty": "300 г",
      "id": 15
    },
    {
      "name": "чесън",
      "qty": "6 скилидки",
      "id": 6
    },
    {
      "name": "зехтин",
      "qty": "6 с.л.",
      "id": 10
    },
    {
      "name": "черен пипер",
      "qty": "1 щип.",
      "id": 2
    },
    {
      "name": "босилек",
      "qty": "Parsing error",
      "id": 25
    },
    {
      "name": "сол",
      "qty": "Parsing error",
      "id": 1
    }
  ]
}