{
  "recipe": {
    "@context": "http://schema.org/",
    "@type": "Recipe",
    "name": "Зеленчукова крем супа от броколи и тиквички",
    "image": [
      "http://www.1001recepti.com/images/photos/recipes/size_4/zelenchukova-krem-supa-ot-brokoli-i-tikvichki-2-[2588].jpg",
      "http://www.1001recepti.com/images/photos/recipes/size_2/zelenchukova-krem-supa-ot-brokoli-i-tikvichki-2-[2588].jpg",
      "http://www.1001recepti.com/images/photos/recipes/size_3/zelenchukova-krem-supa-ot-brokoli-i-tikvichki-2-[2588].jpg"
    ],
    "datePublished": "2013-06-14",
    "cookTime": "PT0H45M",
    "recipeYield": "4 servings",
    "recipeCategory": "Супи",
    "nutrition": {
      "@type": "NutritionInformation",
      "calories": "221 calories",
      "carbohydrateContent": "16 g",
      "fatContent": "14 g",
      "proteinContent": "11 g",
      "saturatedFatContent": "8 g",
      "unsaturatedFatContent": "3.75273 g",
      "cholesterolContent": "48 mg"
    },
    "recipeIngredient": [
      "1/2 кг броколи",
      "1/2 кг тиквички",
      "1 глава лук",
      "1 ч.ч. прясно мляко",
      "100 г сирене",
      "сол",
      "черен пипер",
      "30 г масло"
    ],
    "recipeInstructions": [
      {
        "@type": "HowToStep",
        "text": "Броколите (1/2 кг) се измиват и накъсват на розички, които се сваряват в подсолена вода. Отцеждат се и се оставят настрана. В същия бульон се сваряват тиквичките(1/2 кг), обелени и нарязани на кубчета и обелената глава лук. "
      },
      {
        "@type": "HowToStep",
        "text": "Щом се сварят, се отцеждат и заедно с 2/3 от броколите се пасират. Прибавят се маслото (30 г), мекото сирене (100 г) и прясното мляко (1 ч.ч.). Пак се разбива. Добавя се черният пипер. "
      },
      {
        "@type": "HowToStep",
        "text": "Полученото пюре се връща в бульона и се кипва. Супата се поднася на порции, украсени с цели розички броколи. "
      }
    ]
  },
  "ingredients": [
    {
      "name": "броколи",
      "qty": "1/2 кг",
      "id": 57
    },
    {
      "name": "тиквички",
      "qty": "1/2 кг",
      "id": 39
    },
    {
      "name": "лук",
      "qty": "1 глава",
      "id": 3
    },
    {
      "name": "прясно мляко",
      "qty": "1 ч.ч.",
      "id": 14
    },
    {
      "name": "сирене",
      "qty": "100 г",
      "id": 32
    },
    {
      "name": "сол",
      "qty": "Parsing error",
      "id": 1
    },
    {
      "name": "черен пипер",
      "qty": "Parsing error",
      "id": 2
    },
    {
      "name": "масло",
      "qty": "30 г",
      "id": 8
    }
  ]
}