{
  "recipe": {
    "@context": "http://schema.org/",
    "@type": "Recipe",
    "name": "Крехки и сочни свински ребра с 2 маринати печени под фолио на фурна",
    "image": [
      "http://www.1001recepti.com/images/photos/recipes/size_4/krehki-i-sochni-svinski-rebra-s-marinati-pecheni-pod-folio-na-furna-2-[3417].jpg",
      "http://www.1001recepti.com/images/photos/recipes/size_2/krehki-i-sochni-svinski-rebra-s-marinati-pecheni-pod-folio-na-furna-2-[3417].jpg",
      "http://www.1001recepti.com/images/photos/recipes/size_3/krehki-i-sochni-svinski-rebra-s-marinati-pecheni-pod-folio-na-furna-2-[3417].jpg"
    ],
    "datePublished": "2020-04-17",
    "cookTime": "PT3H0M",
    "recipeYield": "4 servings",
    "recipeCategory": "Основни",
    "nutrition": {
      "@type": "NutritionInformation",
      "calories": "829 calories",
      "carbohydrateContent": "9 g",
      "fatContent": "51 g",
      "proteinContent": "77 g",
      "saturatedFatContent": "17 g",
      "unsaturatedFatContent": "27.89180723301 g",
      "cholesterolContent": "225 mg"
    },
    "recipeIngredient": [
      "1 1/2 кг свински ребра",
      "1 ч.л. черен пипер",
      "1 ч.л. сол",
      "2 ч.л. чесън на прах",
      "3 с.л. червен пипер",
      "1 с.л. горчица",
      "4 с.л. кетчуп",
      "2 с.л. мед",
      "4 с.л. соев сос"
    ],
    "recipeInstructions": [
      {
        "@type": "HowToStep",
        "text": "Свинските ребра (1 1/2 кг) се почистват внимателно от ципата, за да станат по-сочни при печене. "
      },
      {
        "@type": "HowToStep",
        "text": "Приготвя се сухата марината от сол (1 ч.л.), черен пипер (1 ч.л.), чесън на прах (2 ч.л.) и червен пипер (3 с.л.) и се смесват добре. Всяко парче ребра се натрива с маринатата и се обвива във фолио. Пекат се във фурна на 150-160 градуса за около час и половина. "
      },
      {
        "@type": "HowToStep",
        "text": "Приготвя се втората марината, като се разбърква добре горчица (1 с.л.), кетчуп (4 с.л.), мед (2 с.л.) и соев сос (4 с.л.). Ребрата се мажат и от двете страни и се пекат на силна фурна. След това отново се мажат и се допичат."
      },
      {
        "@type": "HowToStep",
        "text": "Течната марината може да се направи и в по-големи колечества и да се използва за сос."
      }
    ]
  },
  "ingredients": [
    {
      "name": "свински ребра",
      "qty": "1 1/2 кг",
      "id": 216
    },
    {
      "name": "черен пипер",
      "qty": "1 ч.л.",
      "id": 2
    },
    {
      "name": "сол",
      "qty": "1 ч.л.",
      "id": 1
    },
    {
      "name": "чесън на прах",
      "qty": "2 ч.л.",
      "id": 6
    },
    {
      "name": "червен пипер",
      "qty": "3 с.л.",
      "id": 20
    },
    {
      "name": "горчица",
      "qty": "1 с.л.",
      "id": 64
    },
    {
      "name": "кетчуп",
      "qty": "4 с.л.",
      "id": 193
    },
    {
      "name": "мед",
      "qty": "2 с.л.",
      "id": 38
    },
    {
      "name": "соев сос",
      "qty": "4 с.л.",
      "id": 53
    }
  ]
}